MANIFEST.in
README.txt
setup.py
examples/__init__.py
teheran_test/__init__.py
teheran_test/article.py
teheran_test/site.py
teheran_test.egg-info/PKG-INFO
teheran_test.egg-info/SOURCES.txt
teheran_test.egg-info/dependency_links.txt
teheran_test.egg-info/requires.txt
teheran_test.egg-info/top_level.txt