Metadata-Version: 2.1
Name: teheran-test
Version: 0.0.1
Summary: A test of web scrapping tool for teherannews.com
Home-page: https://github.com/cesardeaptude/teheran_test
Author: César Pérez Moreno
Author-email: cperez@aptude.com
License: MIT
Platform: UNKNOWN
Requires-Python: >=3
